{"type":"footer","name":"Footer group","sections":{"text-with-icons":{"type":"text-with-icons","blocks":{"item-1":{"type":"item","settings":{"icon":"bi-delivery","title":"Fast Delivery"}},"item-2":{"type":"item","settings":{"icon":"bi-returns","title":"Top Quality"}},"item-3":{"type":"item","settings":{"icon":"bi-customer-support","title":"Customer Support"}},"item-4":{"type":"item","settings":{"icon":"bi-secure-payment","title":"Secure payments"}}},"block_order":["item-1","item-2","item-3","item-4"],"settings":{}},"footer":{"type":"footer","blocks":{"footer-0":{"type":"text","settings":{"title":"About Aipower","content":"<p>Aipower is a Kuwaiti brand specializing in heavy machinery and equipment.<br><br>📍 Shuwaikh Industrial Khalifa Al Jassim Street, Kuwait<br>📞 55000200<br>⏰ Sat-Thur 07:00 AM - 07:00 PM<\/p>"}},"footer-1":{"type":"links","settings":{"title":"Pages","menu":"footer"}},"footer-2":{"type":"links","settings":{"title":"Legal","menu":"legal"}}},"block_order":["footer-0","footer-1","footer-2"],"settings":{"show_social_media":true,"show_payment_icons":true}}},"order":["text-with-icons","footer"]}